uninstaller/__init__.py
uninstaller/__main__.py
uninstaller/uninstaller.py
uninstaller-0.0.2.dist-info/METADATA
uninstaller-0.0.2.dist-info/WHEEL
uninstaller-0.0.2.dist-info/licenses/LICENSE
uninstaller-0.0.2.dist-info/RECORD
