Metadata-Version: 2.1
Name: uninstaller
Version: 0.0.2
Summary: A library for uninstalling packages
Project-URL: GitHub, https://github.com/greyltc/uninstaller
Author-email: Greyson Christoforo <grey@christoforo.net>
License-File: LICENSE
Classifier: Development Status :: 2 - Pre-Alpha
Classifier: License :: OSI Approved :: MIT License
Requires-Python: >=3.10
